<landisMetadata><output><extension name="Biomass Harvest" metadataFilePath="Biomass Harvest.xml" /><fields><field name="Time" description="Harvest Year" unit="year" /><field name="ManagementArea" description="Management Area" /><field name="Prescription" description="Prescription Name" /><field name="Stand" description="Stand" /><field name="EventID" description="Event ID" /><field name="StandAge" description="Stand Age" unit="year" /><field name="StandRank" description="Stand Rank" /><field name="NumberOfSites" description="Number of Sites" unit="count" /><field name="HarvestedSites" description="Number of Sites Harvested" unit="count" /><field name="MgBiomassRemoved" description="Biomass Removed (Mg)" unit="Mg ha-1" format="0.00" /><field name="MgBioRemovedPerDamagedHa" description="Biomass Removed (Mg) per damaged hectare" unit="Mg ha-1" format="0.00" /><field name="TotalCohortsPartialHarvest" description="Number of Cohorts Partially Harvested" unit="count" /><field name="TotalCohortsCompleteHarvest" description="Number of Cohorts Completely Harvested" unit="count" /><field name="CohortsHarvested_CaryOvat" description="Species Cohorts Harvested by Species" unit="count" /><field name="CohortsHarvested_CaryAlba" description="Species Cohorts Harvested by Species" unit="count" /><field name="CohortsHarvested_CornFlor" description="Species Cohorts Harvested by Species" unit="count" /><field name="CohortsHarvested_FraxPenn" description="Species Cohorts Harvested by Species" unit="count" /><field name="CohortsHarvested_FraxAmer" description="Species Cohorts Harvested by Species" unit="count" /><field name="CohortsHarvested_FaguGran" description="Species Cohorts Harvested by Species" unit="count" /><field name="CohortsHarvested_JuglNigr" description="Species Cohorts Harvested by Species" unit="count" /><field name="CohortsHarvested_HaleDipt" description="Species Cohorts Harvested by Species" unit="count" /><field name="CohortsHarvested_IlexOpac" description="Species Cohorts Harvested by Species" unit="count" /><field name="CohortsHarvested_LiriTuli" description="Species Cohorts Harvested by Species" unit="count" /><field name="CohortsHarvested_LiquStyr" description="Species Cohorts Harvested by Species" unit="count" /><field name="CohortsHarvested_MagnAcum" description="Species Cohorts Harvested by Species" unit="count" /><field name="CohortsHarvested_MagnMacr" description="Species Cohorts Harvested by Species" unit="count" /><field name="CohortsHarvested_NyssSylv" description="Species Cohorts Harvested by Species" unit="count" /><field name="CohortsHarvested_OxydArbo" description="Species Cohorts Harvested by Species" unit="count" /><field name="CohortsHarvested_PrunSero" description="Species Cohorts Harvested by Species" unit="count" /><field name="CohortsHarvested_PrunPenn" description="Species Cohorts Harvested by Species" unit="count" /><field name="CohortsHarvested_PlanOcid" description="Species Cohorts Harvested by Species" unit="count" /><field name="CohortsHarvested_QuerAlba" description="Species Cohorts Harvested by Species" unit="count" /><field name="CohortsHarvested_QuerCocc" description="Species Cohorts Harvested by Species" unit="count" /><field name="CohortsHarvested_QuerFalc" description="Species Cohorts Harvested by Species" unit="count" /><field name="CohortsHarvested_QuerRubr" description="Species Cohorts Harvested by Species" unit="count" /><field name="CohortsHarvested_QuerPrin" description="Species Cohorts Harvested by Species" unit="count" /><field name="CohortsHarvested_QuerVelu" description="Species Cohorts Harvested by Species" unit="count" /><field name="CohortsHarvested_QuerStel" description="Species Cohorts Harvested by Species" unit="count" /><field name="CohortsHarvested_RobiPseu" description="Species Cohorts Harvested by Species" unit="count" /><field name="CohortsHarvested_SassAlid" description="Species Cohorts Harvested by Species" unit="count" /><field name="CohortsHarvested_TiliAmer" description="Species Cohorts Harvested by Species" unit="count" /><field name="CohortsHarvested_TiliAmhe" description="Species Cohorts Harvested by Species" unit="count" /><field name="CohortsHarvested_CaryGlab" description="Species Cohorts Harvested by Species" unit="count" /><field name="CohortsHarvested_CaryCodi" description="Species Cohorts Harvested by Species" unit="count" /><field name="CohortsHarvested_BetuNigr" description="Species Cohorts Harvested by Species" unit="count" /><field name="CohortsHarvested_BetuLent" description="Species Cohorts Harvested by Species" unit="count" /><field name="CohortsHarvested_BetuAlle" description="Species Cohorts Harvested by Species" unit="count" /><field name="CohortsHarvested_AcerPens" description="Species Cohorts Harvested by Species" unit="count" /><field name="CohortsHarvested_AmelArbo" description="Species Cohorts Harvested by Species" unit="count" /><field name="CohortsHarvested_AescBuck" description="Species Cohorts Harvested by Species" unit="count" /><field name="CohortsHarvested_AcerRubr" description="Species Cohorts Harvested by Species" unit="count" /><field name="CohortsHarvested_AcerSacc" description="Species Cohorts Harvested by Species" unit="count" /><field name="CohortsHarvested_TsugCana" description="Species Cohorts Harvested by Species" unit="count" /><field name="CohortsHarvested_PinuVirg" description="Species Cohorts Harvested by Species" unit="count" /><field name="CohortsHarvested_PinuTaed" description="Species Cohorts Harvested by Species" unit="count" /><field name="CohortsHarvested_PinuStro" description="Species Cohorts Harvested by Species" unit="count" /><field name="CohortsHarvested_PinuRigi" description="Species Cohorts Harvested by Species" unit="count" /><field name="CohortsHarvested_PinuPung" description="Species Cohorts Harvested by Species" unit="count" /><field name="CohortsHarvested_FrasFirr" description="Species Cohorts Harvested by Species" unit="count" /><field name="CohortsHarvested_PiceRube" description="Species Cohorts Harvested by Species" unit="count" /><field name="CohortsHarvested_PinuEnch" description="Species Cohorts Harvested by Species" unit="count" /><field name="BiomassHarvestedMg_CaryOvat" description="Biomass Harvested by Species (Mg)" unit="" /><field name="BiomassHarvestedMg_CaryAlba" description="Biomass Harvested by Species (Mg)" unit="" /><field name="BiomassHarvestedMg_CornFlor" description="Biomass Harvested by Species (Mg)" unit="" /><field name="BiomassHarvestedMg_FraxPenn" description="Biomass Harvested by Species (Mg)" unit="" /><field name="BiomassHarvestedMg_FraxAmer" description="Biomass Harvested by Species (Mg)" unit="" /><field name="BiomassHarvestedMg_FaguGran" description="Biomass Harvested by Species (Mg)" unit="" /><field name="BiomassHarvestedMg_JuglNigr" description="Biomass Harvested by Species (Mg)" unit="" /><field name="BiomassHarvestedMg_HaleDipt" description="Biomass Harvested by Species (Mg)" unit="" /><field name="BiomassHarvestedMg_IlexOpac" description="Biomass Harvested by Species (Mg)" unit="" /><field name="BiomassHarvestedMg_LiriTuli" description="Biomass Harvested by Species (Mg)" unit="" /><field name="BiomassHarvestedMg_LiquStyr" description="Biomass Harvested by Species (Mg)" unit="" /><field name="BiomassHarvestedMg_MagnAcum" description="Biomass Harvested by Species (Mg)" unit="" /><field name="BiomassHarvestedMg_MagnMacr" description="Biomass Harvested by Species (Mg)" unit="" /><field name="BiomassHarvestedMg_NyssSylv" description="Biomass Harvested by Species (Mg)" unit="" /><field name="BiomassHarvestedMg_OxydArbo" description="Biomass Harvested by Species (Mg)" unit="" /><field name="BiomassHarvestedMg_PrunSero" description="Biomass Harvested by Species (Mg)" unit="" /><field name="BiomassHarvestedMg_PrunPenn" description="Biomass Harvested by Species (Mg)" unit="" /><field name="BiomassHarvestedMg_PlanOcid" description="Biomass Harvested by Species (Mg)" unit="" /><field name="BiomassHarvestedMg_QuerAlba" description="Biomass Harvested by Species (Mg)" unit="" /><field name="BiomassHarvestedMg_QuerCocc" description="Biomass Harvested by Species (Mg)" unit="" /><field name="BiomassHarvestedMg_QuerFalc" description="Biomass Harvested by Species (Mg)" unit="" /><field name="BiomassHarvestedMg_QuerRubr" description="Biomass Harvested by Species (Mg)" unit="" /><field name="BiomassHarvestedMg_QuerPrin" description="Biomass Harvested by Species (Mg)" unit="" /><field name="BiomassHarvestedMg_QuerVelu" description="Biomass Harvested by Species (Mg)" unit="" /><field name="BiomassHarvestedMg_QuerStel" description="Biomass Harvested by Species (Mg)" unit="" /><field name="BiomassHarvestedMg_RobiPseu" description="Biomass Harvested by Species (Mg)" unit="" /><field name="BiomassHarvestedMg_SassAlid" description="Biomass Harvested by Species (Mg)" unit="" /><field name="BiomassHarvestedMg_TiliAmer" description="Biomass Harvested by Species (Mg)" unit="" /><field name="BiomassHarvestedMg_TiliAmhe" description="Biomass Harvested by Species (Mg)" unit="" /><field name="BiomassHarvestedMg_CaryGlab" description="Biomass Harvested by Species (Mg)" unit="" /><field name="BiomassHarvestedMg_CaryCodi" description="Biomass Harvested by Species (Mg)" unit="" /><field name="BiomassHarvestedMg_BetuNigr" description="Biomass Harvested by Species (Mg)" unit="" /><field name="BiomassHarvestedMg_BetuLent" description="Biomass Harvested by Species (Mg)" unit="" /><field name="BiomassHarvestedMg_BetuAlle" description="Biomass Harvested by Species (Mg)" unit="" /><field name="BiomassHarvestedMg_AcerPens" description="Biomass Harvested by Species (Mg)" unit="" /><field name="BiomassHarvestedMg_AmelArbo" description="Biomass Harvested by Species (Mg)" unit="" /><field name="BiomassHarvestedMg_AescBuck" description="Biomass Harvested by Species (Mg)" unit="" /><field name="BiomassHarvestedMg_AcerRubr" description="Biomass Harvested by Species (Mg)" unit="" /><field name="BiomassHarvestedMg_AcerSacc" description="Biomass Harvested by Species (Mg)" unit="" /><field name="BiomassHarvestedMg_TsugCana" description="Biomass Harvested by Species (Mg)" unit="" /><field name="BiomassHarvestedMg_PinuVirg" description="Biomass Harvested by Species (Mg)" unit="" /><field name="BiomassHarvestedMg_PinuTaed" description="Biomass Harvested by Species (Mg)" unit="" /><field name="BiomassHarvestedMg_PinuStro" description="Biomass Harvested by Species (Mg)" unit="" /><field name="BiomassHarvestedMg_PinuRigi" description="Biomass Harvested by Species (Mg)" unit="" /><field name="BiomassHarvestedMg_PinuPung" description="Biomass Harvested by Species (Mg)" unit="" /><field name="BiomassHarvestedMg_FrasFirr" description="Biomass Harvested by Species (Mg)" unit="" /><field name="BiomassHarvestedMg_PiceRube" description="Biomass Harvested by Species (Mg)" unit="" /><field name="BiomassHarvestedMg_PinuEnch" description="Biomass Harvested by Species (Mg)" unit="" /></fields></output></landisMetadata>
